docrag/__init__.py
docrag/_version.py
docrag/core/__init__.py
docrag/core/doc_rag.py
docrag/core/document.py
docrag/core/llm_processing.py
docrag/core/page.py
docrag/core/vector_store.py
docrag/utils/__init__.py
docrag/utils/config.py
docrag/utils/config.yml
docrag/utils/general_utils.py
docrag/utils/log_utils.py
docrag-0.0.3.dist-info/licenses/LICENSE
docrag-0.0.3.dist-info/METADATA
docrag-0.0.3.dist-info/WHEEL
docrag-0.0.3.dist-info/top_level.txt
docrag-0.0.3.dist-info/RECORD
