Metadata-Version: 2.4
Name: docrag
Version: 0.0.3
Summary: DocRag: An advanced document search and retrieval system leveraging Retrieval-Augmented Generation for intelligent natural language search across PDF document collections.
Author-email: Logan Lang <lllang@mix.wvu.edu>
License: 
Project-URL: Repository, https://github.com/lllangWV/DocRag
Project-URL: Issues, https://github.com/lllangWV/DocRag/issues
Keywords: rag,search,pdf,llm,retrieval,documents,vector,embeddings
Classifier: Programming Language :: Python :: 3
Classifier: Programming Language :: Python :: 3.8
Classifier: Programming Language :: Python :: 3.9
Classifier: Programming Language :: Python :: 3.10
Classifier: Programming Language :: Python :: 3.11
Classifier: License :: OSI Approved :: MIT License
Classifier: Topic :: Scientific/Engineering :: Artificial Intelligence
Classifier: Topic :: Text Processing :: Indexing
Requires-Python: >=3.8
License-File: LICENSE
Requires-Dist: python-dotenv
Requires-Dist: numpy
Requires-Dist: pandas
Requires-Dist: matplotlib
Requires-Dist: seaborn
Requires-Dist: requests
Requires-Dist: beautifulsoup4
Requires-Dist: llama-index
Requires-Dist: openai
Requires-Dist: PyPDF2
Requires-Dist: pdf2image
Requires-Dist: Pillow
Requires-Dist: rich
Requires-Dist: pyarrow
Requires-Dist: aiolimiter
Requires-Dist: google-genai
Requires-Dist: opencv-python-headless
Requires-Dist: doclayout-yolo
Requires-Dist: huggingface_hub[cli,hf_transfer]
Provides-Extra: vision
Requires-Dist: opencv-python-headless; extra == "vision"
Provides-Extra: vision-gui
Requires-Dist: opencv-python; extra == "vision-gui"
Provides-Extra: tests
Requires-Dist: pytest; extra == "tests"
Requires-Dist: pytest-cov; extra == "tests"
Provides-Extra: docs
Requires-Dist: ipython; extra == "docs"
Requires-Dist: imageio-ffmpeg; extra == "docs"
Requires-Dist: sphinx; extra == "docs"
Requires-Dist: myst_parser; extra == "docs"
Requires-Dist: sphinx_rtd_theme; extra == "docs"
Requires-Dist: sphinx-copybutton; extra == "docs"
Requires-Dist: nbsphinx; extra == "docs"
Requires-Dist: sphinx_design; extra == "docs"
Requires-Dist: sphinx-new-tab-link; extra == "docs"
Requires-Dist: sphinxcontrib-youtube; extra == "docs"
Requires-Dist: sphinxcontrib-video; extra == "docs"
Requires-Dist: pandoc; extra == "docs"
Requires-Dist: furo; extra == "docs"
Requires-Dist: numpydoc; extra == "docs"
Provides-Extra: dev
Requires-Dist: docrag[dev,docs,tests]; extra == "dev"
Dynamic: license-file
